{
   "abstract" : "Lightweight To-The-Point Email",
   "author" : [
      "Al Newkirk <anewkirk@ana.io>"
   ],
   "dynamic_config" : 0,
   "generated_by" : "ExtUtils::MakeMaker version 6.68, CPAN::Meta::Converter version 2.130880",
   "license" : [
      "perl_5"
   ],
   "meta-spec" : {
      "url" : "http://search.cpan.org/perldoc?CPAN::Meta::Spec",
      "version" : "2"
   },
   "name" : "Emailesque",
   "no_index" : {
      "directory" : [
         "t",
         "inc"
      ]
   },
   "prereqs" : {
      "build" : {
         "requires" : {}
      },
      "configure" : {
         "requires" : {
            "ExtUtils::MakeMaker" : "6.30"
         }
      },
      "runtime" : {
         "requires" : {
            "Authen::SASL" : "0",
            "Email::AddressParser" : "0",
            "Email::Stuffer" : "0",
            "Hash::Merge" : "0.12",
            "IO::Socket::SSL" : "0",
            "Net::SMTP::SSL" : "0",
            "Net::SMTP::TLS" : "0",
            "Net::SSLeay" : "0"
         }
      }
   },
   "release_status" : "stable",
   "version" : "1.200004"
}
